gdmongolite/__init__.py
gdmongolite/advanced_queries.py
gdmongolite/caching.py
gdmongolite/cli.py
gdmongolite/config.py
gdmongolite/core.py
gdmongolite/exceptions.py
gdmongolite/integrations/__init__.py
gdmongolite/integrations/data_import_export.py
gdmongolite/integrations/fastapi.py
gdmongolite/integrations/web_server.py
gdmongolite/migrate/__init__.py
gdmongolite/migrate.py
gdmongolite/monitoring.py
gdmongolite/query.py
gdmongolite/realtime.py
gdmongolite/schema/__init__.py
gdmongolite/security.py
gdmongolite/telemetry.py
gdmongolite/types.py
gdmongolite/utils.py
gdmongolite-1.0.3.dist-info/entry_points.txt
gdmongolite-1.0.3.dist-info/LICENSE
gdmongolite-1.0.3.dist-info/METADATA
gdmongolite-1.0.3.dist-info/WHEEL
gdmongolite-1.0.3.dist-info/RECORD
