Metadata-Version: 2.3
Name: gdmongolite
Version: 1.0.3
Summary: 🚀 The World's Most Powerful and Easiest MongoDB Toolkit - Zero-boilerplate, schema-first MongoDB operations with automatic sync/async detection, advanced queries, real-time features, comprehensive security, caching, monitoring, FastAPI integration, and production-ready deployment tools.
License: MIT
Keywords: mongodb,database,orm,async,pydantic,fastapi,websockets,caching,security,monitoring,migrations,real-time,analytics,aggregation,joins,cli,production,microservices,api
Author: Ganesh Datta Padamata
Author-email: ganeshdattapadamata@gmail.com
Requires-Python: >=3.9,<4.0
Classifier: Development Status :: 5 - Production/Stable
Classifier: Environment :: Web Environment
Classifier: Framework :: AsyncIO
Classifier: Framework :: FastAPI
Classifier: Framework :: Pydantic
Classifier: Intended Audience :: Developers
Classifier: License :: OSI Approved :: MIT License
Classifier: Operating System :: OS Independent
Classifier: Programming Language :: Python :: 3
Classifier: Programming Language :: Python :: 3.9
Classifier: Programming Language :: Python :: 3.10
Classifier: Programming Language :: Python :: 3.11
Classifier: Programming Language :: Python :: 3.12
Classifier: Programming Language :: Python :: 3.13
Classifier: Topic :: Database
Classifier: Topic :: Internet :: WWW/HTTP
Classifier: Topic :: Security
Classifier: Topic :: Software Development :: Libraries :: Application Frameworks
Classifier: Topic :: Software Development :: Libraries :: Python Modules
Classifier: Topic :: System :: Monitoring
Provides-Extra: all
Provides-Extra: redis
Requires-Dist: aioconsole (>=0.6.1,<0.7.0)
Requires-Dist: aiohttp (>=3.9.0,<4.0.0)
Requires-Dist: aioredis (>=2.0.1,<3.0.0) ; extra == "redis" or extra == "all"
Requires-Dist: click (>=8.1.0,<9.0.0)
Requires-Dist: cryptography (>=41.0.0,<42.0.0)
Requires-Dist: fastapi (>=0.104.0,<0.105.0)
Requires-Dist: motor (>=3.6.0,<4.0.0)
Requires-Dist: passlib[bcrypt] (>=1.7.4,<2.0.0)
Requires-Dist: psutil (>=5.9.0,<6.0.0)
Requires-Dist: pydantic[email] (>=2.5.3,<3.0.0)
Requires-Dist: pyjwt (>=2.8.0,<3.0.0)
Requires-Dist: pymongo (>=4.10.0,<5.0.0)
Requires-Dist: python-dotenv (>=1.0.0,<2.0.0)
Requires-Dist: python-jose[cryptography] (>=3.3.0,<4.0.0)
Requires-Dist: pyyaml (>=6.0.1,<7.0.0)
Requires-Dist: rich (>=13.7.0,<14.0.0)
Requires-Dist: uvicorn[standard] (>=0.24.0,<0.25.0)
Requires-Dist: websockets (>=12.0,<13.0)
Project-URL: Bug Tracker, https://github.com/ganeshdatta23/gdmongolite/issues
Project-URL: Changelog, https://github.com/ganeshdatta23/gdmongolite/blob/main/CHANGELOG.md
Project-URL: Documentation, https://gdmongolite.readthedocs.io
Project-URL: Funding, https://github.com/sponsors/ganeshdatta23
Project-URL: Homepage, https://github.com/ganeshdatta23/gdmongolite
Project-URL: Repository, https://github.com/ganeshdatta23/gdmongolite
